{"1PqkR5KNGpdwyrnqFIu3GA==":"03599f8f143ef56-650x866.jpg","VkoIUqKuelFpnz+BJ9qcOA==":"12718175_1144449958921006_7571027004028699220_n-960x960.jpg","XdiAJtVoQSWvGkw297my/A==":"12718175_1144449958921006_7571027004028699220_n-1-960x960.jpg","PcOP8V1iV+9qZWN4ePrZzA==":"fb_img-1475139000400-719x719.jpg","5B8ZrGfP4P6OVr7Kitg/2A==":"family.tourism%202-448x299.jpg","fd05waDDMw3Qq7T8rjODsA==":"135868ba1cf1b99-650x324.jpg","TezOkLCXB9TxivB8GDRJGw==":"unnamed-511x288.jpg","/Revj7lQ22KUYK/N8/tIZw==":"38000352_1093038720871493_2076058595270590464_n-122x183.png","n5Z/4nvFGmFmnmqHk4NFSQ==":"fb_img-1475139000400-240x240.jpg","jF9SUkAKol2kuD6L0AXcVQ==":"fb_img-1475139000401-240x240.jpg","3c4AELjYbbEAu5D2j2QO/g==":"fb_img-1475139000402-240x240.jpg","qWOrVJtJpcVBps6ySAUsCg==":"26196391_1836394883059840_6838162471934645166_n-240x244.jpg","k5b8yHMOjSSISbxUa9eUhg==":"_mg_0370-1-240x360.jpg","NLz0vEETVoETa/AvVMeSeA==":"12718175_1144449958921006_7571027004028699220_n-240x240.jpg","KqqrvpyweYbzeCH9AwrWzw==":"s1-333x500.jpg","RpnNA5qqGTRQy10F3Rc5xg==":"s1-1-333x500.jpg","kC89uAkyx2uRnMbcRhogFQ==":"images-82x86.png","CWc34lx4CqGyjYN5ODnzog==":"prevention-icon-118x118.png","r32B6hvpu5ggZKIbpB2NMA==":"1536070261207-722x399.jpg","Qo298VJK/W8/9e9UHZrO4Q==":"1536070261207-1-722x399.jpg","ocX8wBBTmezqxD5v25aUcA==":"unnamed%202-511x288.jpg","u8VXUQb/ioZ3QzmlAzjR8A==":"1536070261207-2-722x399.jpg","ModW0FC3kT76h6NnZrhRJg==":"unnamed%202-511x288.jpg","8BovIJlvFse6lVJyBlQRZQ==":"9559999fc3af68b-650x406.jpg","szktNMzDGTCPTdmOfMMAdw==":"1536111108470-720x480.jpg","g9UmGBwQqMZqLEDL/jhUCQ==":"1536111108470-1-720x480.jpg","72/8Baakm9aefhVD8OTz0Q==":"1536111108470-2-720x480.jpg","bFp0JKy1Piy90Ooj2zXngw==":"1536111108470-3-720x480.jpg","cCBd/3vBSWwHn1FhoRVRWQ==":"1536111446451-952x726.jpg","mHgRjTp+4J/xZn/3yY72jA==":"1536109830936-720x449.jpg","n4dBa3dBNcwhEez12Out/A==":"1536111446451-1-952x726.jpg","/ODq3nzFTCrF6f0ZElscWQ==":"1536110846997-720x417.jpg","RNMYy6xcNSbdwxgC4MjDdw==":"1536108874363-720x359.jpg","0Gzv/dEcAlXR0foQg8kztg==":"images%20(5)-680x451.jpg","e1zih3rqKdBZgvz3cwbFGw==":"images%20(6)-744x412.jpg","tFDu/BX/TZcOPY3BiiaJZQ==":"1647517-image-1519846950-107-640x480.jpg","YNvv0dTdcMr1aAduIrILBw==":"1647517-image-1519846950-108-640x480.jpg","8iZblKBviZnQ4b5wn5a8Aw==":"mbr-1920x1355.jpg","wPSdwPJTyNLxNP7eZthjRA==":"mbr-1920x1280.jpg","w7TDcqczCojASTxeU977+w==":"mbr-1-1920x1280.jpg","8hdM9eke3uREEe+rfDRBBg==":"mbr-2-1920x1280.jpg","8JBT2WKlk5L5lX9sEpijDQ==":"mbr-1-1920x1355.jpg","ouINO3yybmspqBLNX+v+OA==":"mbr-2-1920x1355.jpg","FYDG/AyeZRcrrO4hqvha0A==":"mbr-3-1920x1355.jpg","ZH3od9H/ITe6E4xLJO9YPw==":"mbr-4-1920x1355.jpg","TDAWFupUdC/AqI8sGm0pmA==":"mbr-5-1920x1355.jpg","MOeoMfESY4rYgH0jcHTUkw==":"mbr-6-1920x1355.jpg","zd7Zi8lQdyBuNexUMXTxzw==":"world-population-498728-122x122.png","Bo/BT0v2eqWX1qo89IG2sg==":"world-population-498728-192x192.png","BtuDx6zgtJ3vvOFDknW9VQ==":"world-population-498729-192x192.png","GGVOdwX+CktOIUhA2m4atQ==":"prevention-icon-192x192.png","1D20AHpWaDu2h0d2FocnHg==":"41104648_222739058598368_7883259321864159232_n-261x185.png","il5Uw8AR2UO9fvXhHrl79A==":"41078783_503819243419317_4978686708968062976_n-2000x1125.jpg","aOIyN4tJUdwctycZi/iAyg==":"small1-2000x1125.jpg","1jV0aozJfidaVE9G77BmaA==":"load-2000x1125.jpg","nm1mW9bNzEeBpbVKrQH53Q==":"41092917_494749480991177_3192373904635068416_n-261x185.png","5Jb5JdKYv99JT9BqjMBFOQ==":"41039215_386189098868891_7885989946106839040_n-2000x1125.jpg","ihlkf69UyfSmhSyJ1Jvc6w==":"jumbotron.jpg","cSZvjJjbs7UpaeCAPSHn+w==":"andrewbadge4___bq2p6-8j0i4___-676x507.jpg","t/zHrY5vQQUzMQudbgOBuA==":"andrewbadge4___bogomuda3vz___-676x575.jpg","px1ICgIzno+bpILVH2Ms3g==":"andrewbadge4___bogomuda3vz___-1-676x575.jpg","7LWPwQYn6R1yl+KTZJVN4Q==":"andrewbadge4___bq2p6-8j0i4___-1-676x507.jpg","UAl3+2Xu6UKxGpeyRsBmew==":"andrewbadge4___zutt05jlxm___-640x640.jpg","VAV43mT0oQrX9EIdFgFMBg==":"fb_img-1536669444486-512x384.jpg","xwivTWPYDXdxK20hkYo20w==":"fb_img-1536669444487-512x384.jpg","/qE/LsCI2BrHh659bX6tWg==":"fb_img-1536669444486-492x369.jpg","mtBvh3518oiA1kSSghwq6w==":"andrewbadge4___bq2p6-8j0i4___-492x369.jpg","yMNYVr8/iZ3hE6+02eRwJg==":"andrewbadge4___bogomuda3vz___-492x418.jpg","+b1SMQMTxGDxBkF2LHqcnA==":"andrewbadge4___zutt05jlxm___-492x492.jpg","poUREfxTf1VWjqeMVn1dcw==":"fb_img-1536669444487-492x369.jpg","XARZq6Leco9+icttrCBbtQ==":"andrewbadge4___bpvumtkaaww___-1080x1080.jpg","jwHEgHcimcqTLxQTEAUgVA==":"file-20180820-30587-11272h0-668x324.jpg","q7mgbyMfcZNjFlayuwB5rw==":"p_20180912-75448-492x277.jpg","i1QvTiMXUeb9JHxwtGusbA==":"p_20180912-80523-492x277.jpg","XWFMPqg4yi2CsqRKIWgmYA==":"p_20180912-83402-492x277.jpg","1jY7n3g8SCbti154jqaqBQ==":"p_20180912-83203-492x277.jpg","k4DvxnSdFj4lzPrFQVe5+Q==":"p_20180906-185857-402x226.jpg","vJzx/EKljhWuuDl3BVohHg==":"andrewbadge4___bq2p6-8j0i4___-1080x810.jpg","0/9Iuz1PD3FkgLK2vQyFSA==":"andrewbadge4___bogomuda3vz___-1080x918.jpg","/qWf4OdJescyPlr9EzygrQ==":"andrewbadge4___zutt05jlxm___-1-640x640.jpg","Ig3f719IsvA3fyqYnIlnuw==":"fb_img-1536669444488-512x384.jpg","WPzYmFswTQlTqn5ihC/KGg==":"p_20180912-75448-2000x1125.jpg","3/sIBUy9epJvuQRGJRAyzQ==":"p_20180912-80523-2000x1125.jpg","zW6aAflyxCJf5cH2s4kccA==":"p_20180906-185857-2000x1125.jpg","fvrI6ai1BldnaQBTgVwVkg==":"p_20180912-83402-2000x1125.jpg","eGJ6hCJ2KiQTKJ87rVXRZQ==":"andrewbadge4___bq2p6-8j0i4___-1-1080x810.jpg","mv1c9v6r0JxyMcAIBGjp5w==":"andrewbadge4___bogomuda3vz___-1-1080x918.jpg","GPF4NEyjSjf4oJcH+MCNFQ==":"file-20180820-30587-11272h0-1-668x324.jpg","BWJ3JPfTCActRdzsY84ZRw==":"andrewbadge4___bpvumtkaaww___-1-1080x1080.jpg","86pXYry5do7Mlf+P6AheZw==":"andrewbadge4___bogomuda3vz___-2-1080x918.jpg","85ZOAOXai9/C1EZl3iZsNg==":"img_20150603-85812-1023x680.jpg","/qAraC/FV3wpFl2JP148aA==":"img_20160717-205049-500x750.jpg","gxeqD31WdvPy0mztq1frgA==":"img_20160209-55639-1024x489.jpg","sfAUjzpSqG9GxG3AImjk9Q==":"unnamed-1-511x288.jpg","Af1qJr4EVFABqwZ2qnkO8w==":"591432970-612x408.jpg"}